PartyBotPackage/__init__.py
FranciscophkBot-1.1.dist-info/LICENSE
FranciscophkBot-1.1.dist-info/METADATA
FranciscophkBot-1.1.dist-info/WHEEL
FranciscophkBot-1.1.dist-info/top_level.txt
FranciscophkBot-1.1.dist-info/RECORD
