Metadata-Version: 2.1
Name: FranciscophkBot
Version: 1.2
Summary: PartyBot in a PyPi package form to easily be ran on repl.
Home-page: https://github.com/xMistt/fortnitepy-bot
Author: Franciscophk
License: UNKNOWN
Platform: UNKNOWN
Classifier: Programming Language :: Python :: 3
Classifier: License :: OSI Approved :: MIT License
Classifier: Operating System :: OS Independent
Requires-Dist: crayons
Requires-Dist: fortnitepy
Requires-Dist: BenBotAsync
Requires-Dist: FortniteAPIAsync
Requires-Dist: uvloop
Requires-Dist: sanic
Requires-Dist: aiohttp
